streamlit_kpi_card/__init__.py
streamlit_kpi_card/frontend/build/index.html
streamlit_kpi_card/frontend/build/assets/index-B7invOdc.js
streamlit_kpi_card-0.1.2.dist-info/LICENSE
streamlit_kpi_card-0.1.2.dist-info/METADATA
streamlit_kpi_card-0.1.2.dist-info/WHEEL
streamlit_kpi_card-0.1.2.dist-info/top_level.txt
streamlit_kpi_card-0.1.2.dist-info/RECORD
