Metadata-Version: 2.1
Name: streamlit-kpi-card
Version: 0.1.2
Summary: A beautiful, interactive KPI card component for Streamlit with time series visualization
Author: pjoachims
License: MIT
Project-URL: Homepage, https://github.com/pjoachims/streamlit-kpi-card
Project-URL: Repository, https://github.com/pjoachims/streamlit-kpi-card
Project-URL: Issues, https://github.com/pjoachims/streamlit-kpi-card/issues
Keywords: streamlit,kpi,card,metrics,dashboard,visualization
Classifier: Development Status :: 4 - Beta
Classifier: Intended Audience :: Developers
Classifier: License :: OSI Approved :: MIT License
Classifier: Operating System :: OS Independent
Classifier: Programming Language :: Python :: 3
Classifier: Programming Language :: Python :: 3.7
Classifier: Programming Language :: Python :: 3.8
Classifier: Programming Language :: Python :: 3.9
Classifier: Programming Language :: Python :: 3.10
Classifier: Programming Language :: Python :: 3.11
Classifier: Topic :: Software Development :: Libraries :: Python Modules
Requires-Python: >=3.7
License-File: LICENSE
Requires-Dist: streamlit>=1.0.0
Requires-Dist: pandas>=1.0.0
